{"acqNameList":["Samvardhana Motherson International Ltd","RADHA RANI HOLDINGS PTE LIMITED","GEETA SONI","ALOK GOEL","G.N. GAUBA","PANKAJ MITAL","NAVEEN GANZU","GEETA MATHUR","Arjun Puri","NILU MEHRA","LAKSH VAAMAN SEHGAL","RENU ALKA SEHGAL","VIVEK CHAAND SEHGAL","SaSamvardhana Motherson International Ltd","Sumitomo Wiring Systems Limited"],"data":[{"symbol":"MOTHERSUMI","company":"Motherson Sumi Systems Limited","anex":"7(2)","acqName":"Samvardhana Motherson International Ltd","date":"27-Aug-2021 16:17","pid":"1108933","tkdAcqm":null,"buyValue":"0","sellValue":"0","buyQuantity":"0","sellquantity":"0","secType":"Equity Shares","secAcq":"10000000","did":"385293","tdpTransactionType":"Pledge","tdpDerivativeContractType":"-","xbrl":"https://archives.nseindia.com/corporate/xbrl/IT_1108933_511139_27082021041750_WEB.xml","personCategory":"Promoters","befAcqSharesNo":"1055750653","befAcqSharesPer":"33.43","secVal":"2114000000","securitiesTypePost":"Equity Shares","afterAcqSharesNo":"1055750653","afterAcqSharesPer":"33.43","acqfromDt":"25-Aug-2021","acqtoDt":"25-Aug-2021","intimDt":"26-Aug-2021","acqMode":"Pledge Creation","derivativeType":"-","exchange":"NA","remarks":"-"},{"symbol":"MOTHERSUMI","company":"Motherson Sumi Systems Limited","anex":"7(2)","acqName":"RADHA RANI HOLDINGS PTE LIMITED","date":"11-Aug-2021 17:54","pid":"1107254","tkdAcqm":null,"buyValue":"0","sellValue":"0","buyQuantity":"0","sellquantity":"0","secType":"Equity Shares","secAcq":"3442623","did":"380705","tdpTransactionType":"Pledge","tdpDerivativeContractType":"-","xbrl":"https://archives.nseindia.com/corporate/xbrl/IT_1107254_503483_11082021055425_WEB.xml","personCategory":"Promoter Group","befAcqSharesNo":"3442623","befAcqSharesPer":"0.11","secVal":"812975421","securitiesTypePost":"Equity Shares","afterAcqSharesNo":"3442623","afterAcqSharesPer":"0.11","acqfromDt":"06-Aug-2021","acqtoDt":"06-Aug-2021","intimDt":"09-Aug-2021","acqMode":"Pledge Creation","derivativeType":"-","exchange":"NA","remarks":"-"},{"symbol":"MOTHERSUMI","company":"Motherson Sumi Systems Limited","anex":"7(2)","acqName":"Samvardhana Motherson International Ltd","date":"10-Jun-2021 14:31","pid":"1101952","tkdAcqm":null,"buyValue":"0","sellValue":"0","buyQuantity":"0","sellquantity":"0","secType":"Equity Shares","secAcq":"10000000","did":"366271","tdpTransactionType":"Pledge","tdpDerivativeContractType":"-","xbrl":"https://archives.nseindia.com/corporate/xbrl/IT_1101952_457293_10062021023115_WEB.xml","personCategory":"Promoters","befAcqSharesNo":"1055750653","befAcqSharesPer":"33.43","secVal":"2520500000","securitiesTypePost":"Equity Shares","afterAcqSharesNo":"1055750653","afterAcqSharesPer":"33.43","acqfromDt":"07-Jun-2021","acqtoDt":"07-Jun-2021","intimDt":"09-Jun-2021","acqMode":"Revokation of Pledge","derivativeType":"-","exchange":"NA","remarks":"-"},{"symbol":"MOTHERSUMI","company":"Motherson Sumi Systems Limited","anex":"7(2)","acqName":"Samvardhana Motherson International Ltd","date":"11-Mar-2021 18:51","pid":"1094841","tkdAcqm":null,"buyValue":"0","sellValue":"0","buyQuantity":"0","sellquantity":"0","secType":"Equity Shares","secAcq":"37000000","did":"346972","tdpTransactionType":"Pledge Revoke","tdpDerivativeContractType":"-","xbrl":"https://archives.nseindia.com/corporate/xbrl/IT_1094841_415981_11032021065109_WEB.xml","personCategory":"Promoters","befAcqSharesNo":"1055750653","befAcqSharesPer":"33.43","secVal":"8008650000","securitiesTypePost":"Equity Shares","afterAcqSharesNo":"1055750653","afterAcqSharesPer":"33.43","acqfromDt":"09-Mar-2021","acqtoDt":"09-Mar-2021","intimDt":"10-Mar-2021","acqMode":"Revokation of Pledge","derivativeType":"-","exchange":"NA","remarks":"-"},{"symbol":"MOTHERSUMI","company":"Motherson Sumi Systems Limited","anex":"7(2)","acqName":"Samvardhana Motherson International Ltd","date":"19-Feb-2021 15:33","pid":"1092067","tkdAcqm":null,"buyValue":"0","sellValue":"0","buyQuantity":"0","sellquantity":"0","secType":"Equity Shares","secAcq":"21230000","did":"340162","tdpTransactionType":"Pledge Revoke","tdpDerivativeContractType":"-","xbrl":"https://archives.nseindia.com/corporate/xbrl/IT_1092067_411490_19022021033303_WEB.xml","personCategory":"Promoters","befAcqSharesNo":"1055750653","befAcqSharesPer":"33.43","secVal":"4685461000","securitiesTypePost":"Equity Shares","afterAcqSharesNo":"1055750653","afterAcqSharesPer":"33.43","acqfromDt":"18-Feb-2021","acqtoDt":"18-Feb-2021","intimDt":"19-Feb-2021","acqMode":"Revokation of Pledge","derivativeType":"-","exchange":"NA","remarks":"-"},{"symbol":"MOTHERSUMI","company":"Motherson Sumi Systems Limited","anex":"7(2)","acqName":"Samvardhana Motherson International Ltd","date":"24-Dec-2020 18:32","pid":"1087907","tkdAcqm":null,"buyValue":"0","sellValue":"0","buyQuantity":"0","sellquantity":"0","secType":"Equity Shares","secAcq":"27600000","did":"328922","tdpTransactionType":"Pledge Revoke","tdpDerivativeContractType":"-","xbrl":"https://archives.nseindia.com/corporate/xbrl/IT_1087907_373323_24122020063225_WEB.xml","personCategory":"Promoters","befAcqSharesNo":"1055750653","befAcqSharesPer":"33.43","secVal":"4180020000","securitiesTypePost":"Equity Shares","afterAcqSharesNo":"1055750653","afterAcqSharesPer":"33.43","acqfromDt":"23-Dec-2020","acqtoDt":"23-Dec-2020","intimDt":"24-Dec-2020","acqMode":"Revokation of Pledge","derivativeType":"-","exchange":"NA","remarks":"-"},{"symbol":"MOTHERSUMI","company":"Motherson Sumi Systems Limited","anex":"7(2)","acqName":"Samvardhana Motherson International Ltd","date":"27-Nov-2020 18:03","pid":"1084774","tkdAcqm":null,"buyValue":"0","sellValue":"0","buyQuantity":"0","sellquantity":"0","secType":"Equity Shares","secAcq":"2270000","did":"320420","tdpTransactionType":"Pledge Revoke","tdpDerivativeContractType":"-","xbrl":"https://archives.nseindia.com/corporate/xbrl/IT_1084774_366938_27112020060354_WEB.xml","personCategory":"Promoters","befAcqSharesNo":"1055750653","befAcqSharesPer":"33.43","secVal":"329944500","securitiesTypePost":"Equity Shares","afterAcqSharesNo":"1055750653","afterAcqSharesPer":"33.43","acqfromDt":"24-Nov-2020","acqtoDt":"24-Nov-2020","intimDt":"25-Nov-2020","acqMode":"Revokation of Pledge","derivativeType":"-","exchange":"NA","remarks":"-"},{"symbol":"MOTHERSUMI","company":"Motherson Sumi Systems Limited","anex":"7(2)","acqName":"Samvardhana Motherson International Ltd","date":"27-Nov-2020 18:03","pid":"1084774","tkdAcqm":null,"buyValue":"0","sellValue":"0","buyQuantity":"0","sellquantity":"0","secType":"Equity Shares","secAcq":"22326512","did":"320421","tdpTransactionType":"Pledge Revoke","tdpDerivativeContractType":"-","xbrl":"https://archives.nseindia.com/corporate/xbrl/IT_1084774_366938_27112020060354_WEB.xml","personCategory":"Promoters","befAcqSharesNo":"1055750653","befAcqSharesPer":"33.43","secVal":"3245158519","securitiesTypePost":"Equity Shares","afterAcqSharesNo":"1055750653","afterAcqSharesPer":"33.43","acqfromDt":"24-Nov-2020","acqtoDt":"24-Nov-2020","intimDt":"25-Nov-2020","acqMode":"Revokation of Pledge","derivativeType":"-","exchange":"NA","remarks":"-"},{"symbol":"MOTHERSUMI","company":"Motherson Sumi Systems Limited","anex":"7(2)","acqName":"Samvardhana Motherson International Ltd","date":"10-Oct-2020 12:44","pid":"1081779","tkdAcqm":null,"buyValue":"0","sellValue":"0","buyQuantity":"0","sellquantity":"0","secType":"Equity Shares","secAcq":"16000000","did":"311495","tdpTransactionType":"Pledge Revoke","tdpDerivativeContractType":"-","xbrl":"https://archives.nseindia.com/corporate/xbrl/IT_1081779_332399_10102020124439_WEB.xml","personCategory":"Promoters","befAcqSharesNo":"1055750653","befAcqSharesPer":"33.43","secVal":"1866400000","securitiesTypePost":"Equity Shares","afterAcqSharesNo":"1055750653","afterAcqSharesPer":"33.43","acqfromDt":"06-Oct-2020","acqtoDt":"06-Oct-2020","intimDt":"08-Oct-2020","acqMode":"Revokation of Pledge","derivativeType":"-","exchange":"NA","remarks":"-"},{"symbol":"MOTHERSUMI","company":"Motherson Sumi Systems Limited","anex":"7(2)","acqName":"Samvardhana Motherson International Ltd","date":"27-Aug-2020 11:47","pid":"1077477","tkdAcqm":null,"buyValue":"0","sellValue":"0","buyQuantity":"0","sellquantity":"0","secType":"Equity Shares","secAcq":"9000000","did":"301854","tdpTransactionType":"Pledge Revoke","tdpDerivativeContractType":"-","xbrl":"https://archives.nseindia.com/corporate/xbrl/IT_1077477_310851_27082020114717_WEB.xml","personCategory":"Promoters","befAcqSharesNo":"1055750653","befAcqSharesPer":"33.43","secVal":"1057950000","securitiesTypePost":"Equity Shares","afterAcqSharesNo":"1055750653","afterAcqSharesPer":"33.43","acqfromDt":"21-Aug-2020","acqtoDt":"21-Aug-2020","intimDt":"25-Aug-2020","acqMode":"Revokation of Pledge","derivativeType":"-","exchange":"NA","remarks":"-"},{"symbol":"MOTHERSUMI","company":"Motherson Sumi Systems Limited","anex":"7(2)","acqName":"Samvardhana Motherson International Ltd","date":"24-Aug-2020 17:15","pid":"1077145","tkdAcqm":null,"buyValue":"0","sellValue":"0","buyQuantity":"0","sellquantity":"0","secType":"Equity Shares","secAcq":"6985327","did":"301053","tdpTransactionType":"Pledge Revoke","tdpDerivativeContractType":"-","xbrl":"https://archives.nseindia.com/corporate/xbrl/IT_1077145_309974_24082020051525_WEB.xml","personCategory":"Promoters","befAcqSharesNo":"1055750653","befAcqSharesPer":"33.43","secVal":"833698777","securitiesTypePost":"Equity Shares","afterAcqSharesNo":"1055750653","afterAcqSharesPer":"33.43","acqfromDt":"20-Aug-2020","acqtoDt":"20-Aug-2020","intimDt":"21-Aug-2020","acqMode":"Revokation of Pledge","derivativeType":"-","exchange":"NA","remarks":"-"},{"symbol":"MOTHERSUMI","company":"Motherson Sumi Systems Limited","anex":"7(2)","acqName":"Samvardhana Motherson International Ltd","date":"21-Apr-2020 20:33","pid":"1072054","tkdAcqm":null,"buyValue":"0","sellValue":"0","buyQuantity":"0","sellquantity":"0","secType":"Equity Shares","secAcq":"5000000","did":"286105","tdpTransactionType":"Pledge Revoke","tdpDerivativeContractType":"-","xbrl":"https://archives.nseindia.com/corporate/xbrl/IT_1072054_242311_21042020083339_WEB.xml","personCategory":"Promoters","befAcqSharesNo":"1055750653","befAcqSharesPer":"33.43","secVal":"434000000","securitiesTypePost":"Equity Shares","afterAcqSharesNo":"1055750653","afterAcqSharesPer":"33.43","acqfromDt":"17-Apr-2020","acqtoDt":"17-Apr-2020","intimDt":"20-Apr-2020","acqMode":"Revokation of Pledge","derivativeType":"-","exchange":"NA","remarks":"-"},{"symbol":"MOTHERSUMI","company":"Motherson Sumi Systems Limited","anex":"7(2)","acqName":"Samvardhana Motherson International Ltd","date":"16-Apr-2020 00:06","pid":"1071960","tkdAcqm":null,"buyValue":"0","sellValue":"0","buyQuantity":"0","sellquantity":"0","secType":"Equity Shares","secAcq":"30485326","did":"285926","tdpTransactionType":"Pledge Revoke","tdpDerivativeContractType":"-","xbrl":"https://archives.nseindia.com/corporate/xbrl/IT_1071960_239498_16042020120636_WEB.xml","personCategory":"Promoter Group","befAcqSharesNo":"1055750653","befAcqSharesPer":"33.43","secVal":"1925148337","securitiesTypePost":"Equity Shares","afterAcqSharesNo":"1055750653","afterAcqSharesPer":"33.43","acqfromDt":"13-Apr-2020","acqtoDt":"13-Apr-2020","intimDt":"15-Apr-2020","acqMode":"Revokation of Pledge","derivativeType":"-","exchange":"NA","remarks":"-"},{"symbol":"MOTHERSUMI","company":"Motherson Sumi Systems Limited","anex":"7(2)","acqName":"Samvardhana Motherson International Ltd","date":"15-Apr-2020 20:04","pid":"1071956","tkdAcqm":null,"buyValue":"0","sellValue":"0","buyQuantity":"0","sellquantity":"0","secType":"Equity Shares","secAcq":"5500000","did":"285914","tdpTransactionType":"Pledge","tdpDerivativeContractType":"-","xbrl":"https://archives.nseindia.com/corporate/xbrl/IT_1071956_239408_15042020080443_WEB.xml","personCategory":"Promoters","befAcqSharesNo":"1055750653","befAcqSharesPer":"33.43","secVal":"363275000","securitiesTypePost":"Equity Shares","afterAcqSharesNo":"1055750653","afterAcqSharesPer":"33.43","acqfromDt":"09-Apr-2020","acqtoDt":"09-Apr-2020","intimDt":"13-Apr-2020","acqMode":"Pledge Creation","derivativeType":"-","exchange":"NA","remarks":"-"},{"symbol":"MOTHERSUMI","company":"Motherson Sumi Systems Limited","anex":"7(2)","acqName":"Samvardhana Motherson International Ltd","date":"23-Mar-2020 18:07","pid":"1069988","tkdAcqm":null,"buyValue":"0","sellValue":"0","buyQuantity":"0","sellquantity":"0","secType":"Equity Shares","secAcq":"24500000","did":"282025","tdpTransactionType":"Pledge","tdpDerivativeContractType":"-","xbrl":"https://archives.nseindia.com/corporate/xbrl/IT_1069988_232291_23032020060739_WEB.xml","personCategory":"Promoters","befAcqSharesNo":"1055750653","befAcqSharesPer":"33.43","secVal":"1634150000","securitiesTypePost":"Equity Shares","afterAcqSharesNo":"1055750653","afterAcqSharesPer":"33.43","acqfromDt":"20-Mar-2020","acqtoDt":"20-Mar-2020","intimDt":"23-Mar-2020","acqMode":"Pledge Creation","derivativeType":"-","exchange":"NA","remarks":"-"},{"symbol":"MOTHERSUMI","company":"Motherson Sumi Systems Limited","anex":"7(2)","acqName":"Samvardhana Motherson International Ltd","date":"13-Mar-2020 12:34","pid":"1068187","tkdAcqm":null,"buyValue":"0","sellValue":"0","buyQuantity":"0","sellquantity":"0","secType":"Equity Shares","secAcq":"40600000","did":"278327","tdpTransactionType":"Pledge Revoke","tdpDerivativeContractType":"-","xbrl":"https://archives.nseindia.com/corporate/xbrl/IT_1068187_228876_13032020123452_WEB.xml","personCategory":"Promoters","befAcqSharesNo":"1055750653","befAcqSharesPer":"33.43","secVal":"2756740000","securitiesTypePost":"Equity Shares","afterAcqSharesNo":"1055750653","afterAcqSharesPer":"33.43","acqfromDt":"13-Mar-2020","acqtoDt":"13-Mar-2020","intimDt":"13-Mar-2020","acqMode":"Revokation of Pledge","derivativeType":"-","exchange":"NA","remarks":"-"},{"symbol":"MOTHERSUMI","company":"Motherson Sumi Systems Limited","anex":"7(2)","acqName":"Samvardhana Motherson International Ltd","date":"13-Mar-2020 12:34","pid":"1068187","tkdAcqm":null,"buyValue":"0","sellValue":"0","buyQuantity":"0","sellquantity":"0","secType":"Equity Shares","secAcq":"7760653","did":"278328","tdpTransactionType":"Pledge","tdpDerivativeContractType":"-","xbrl":"https://archives.nseindia.com/corporate/xbrl/IT_1068187_228876_13032020123452_WEB.xml","personCategory":"Promoters","befAcqSharesNo":"1055750653","befAcqSharesPer":"33.43","secVal":"526948339","securitiesTypePost":"Equity Shares","afterAcqSharesNo":"1055750653","afterAcqSharesPer":"33.43","acqfromDt":"12-Mar-2020","acqtoDt":"12-Mar-2020","intimDt":"13-Mar-2020","acqMode":"Pledge Creation","derivativeType":"-","exchange":"NA","remarks":"-"},{"symbol":"MOTHERSUMI","company":"Motherson Sumi Systems Limited","anex":"7(2)","acqName":"Samvardhana Motherson International Ltd","date":"13-Mar-2020 12:25","pid":"1068184","tkdAcqm":null,"buyValue":"0","sellValue":"0","buyQuantity":"0","sellquantity":"0","secType":"Equity Shares","secAcq":"25830000","did":"278322","tdpTransactionType":"Pledge","tdpDerivativeContractType":"-","xbrl":"https://archives.nseindia.com/corporate/xbrl/IT_1068184_228860_13032020122550_WEB.xml","personCategory":"Promoters","befAcqSharesNo":"1055750653","befAcqSharesPer":"33.43","secVal":"2318242500","securitiesTypePost":"Equity Shares","afterAcqSharesNo":"1055750653","afterAcqSharesPer":"33.43","acqfromDt":"11-Mar-2020","acqtoDt":"11-Mar-2020","intimDt":"12-Mar-2020","acqMode":"Pledge Creation","derivativeType":"-","exchange":"NA","remarks":"-"},{"symbol":"MOTHERSUMI","company":"Motherson Sumi Systems Limited","anex":"7(2)","acqName":"Samvardhana Motherson International Ltd","date":"13-Mar-2020 12:25","pid":"1068184","tkdAcqm":null,"buyValue":"0","sellValue":"0","buyQuantity":"0","sellquantity":"0","secType":"Equity Shares","secAcq":"8150000","did":"278321","tdpTransactionType":"Pledge","tdpDerivativeContractType":"-","xbrl":"https://archives.nseindia.com/corporate/xbrl/IT_1068184_228860_13032020122550_WEB.xml","personCategory":"Promoters","befAcqSharesNo":"1055750653","befAcqSharesPer":"33.43","secVal":"731462500","securitiesTypePost":"Equity Shares","afterAcqSharesNo":"1055750653","afterAcqSharesPer":"33.43","acqfromDt":"11-Mar-2020","acqtoDt":"11-Mar-2020","intimDt":"12-Mar-2020","acqMode":"Pledge Creation","derivativeType":"-","exchange":"NA","remarks":"-"},{"symbol":"MOTHERSUMI","company":"Motherson Sumi Systems Limited","anex":"7(2)","acqName":"Samvardhana Motherson International Ltd","date":"02-Mar-2020 18:51","pid":"1066985","tkdAcqm":null,"buyValue":"0","sellValue":"0","buyQuantity":"0","sellquantity":"0","secType":"Equity Shares","secAcq":"4150000","did":"275999","tdpTransactionType":"Pledge","tdpDerivativeContractType":"-","xbrl":"https://archives.nseindia.com/corporate/xbrl/IT_1066985_226599_02032020065100_WEB.xml","personCategory":"Promoters","befAcqSharesNo":"1055750653","befAcqSharesPer":"33.43","secVal":"452765000","securitiesTypePost":"Equity Shares","afterAcqSharesNo":"1055750653","afterAcqSharesPer":"33.43","acqfromDt":"27-Feb-2020","acqtoDt":"27-Feb-2020","intimDt":"29-Feb-2020","acqMode":"Pledge Creation","derivativeType":"-","exchange":"NA","remarks":"-"},{"symbol":"MOTHERSUMI","company":"Motherson Sumi Systems Limited","anex":"7(2)","acqName":"Samvardhana Motherson International Ltd","date":"02-Mar-2020 18:51","pid":"1066985","tkdAcqm":null,"buyValue":"0","sellValue":"0","buyQuantity":"0","sellquantity":"0","secType":"Equity Shares","secAcq":"29280000","did":"276000","tdpTransactionType":"Pledge","tdpDerivativeContractType":"-","xbrl":"https://archives.nseindia.com/corporate/xbrl/IT_1066985_226599_02032020065100_WEB.xml","personCategory":"Promoters","befAcqSharesNo":"1055750653","befAcqSharesPer":"33.43","secVal":"3194448000","securitiesTypePost":"Equity Shares","afterAcqSharesNo":"1055750653","afterAcqSharesPer":"33.43","acqfromDt":"27-Feb-2020","acqtoDt":"27-Feb-2020","intimDt":"29-Feb-2020","acqMode":"Pledge Creation","derivativeType":"-","exchange":"NA","remarks":"-"},{"symbol":"MOTHERSUMI","company":"Motherson Sumi Systems Limited","anex":"7(2)","acqName":"Samvardhana Motherson International Ltd","date":"20-Feb-2020 19:24","pid":"1066031","tkdAcqm":null,"buyValue":"0","sellValue":"0","buyQuantity":"0","sellquantity":"0","secType":"Equity Shares","secAcq":"15176271","did":"273936","tdpTransactionType":"Pledge","tdpDerivativeContractType":"-","xbrl":"https://archives.nseindia.com/corporate/xbrl/IT_1066031_224411_20022020072427_WEB.xml","personCategory":"Promoters","befAcqSharesNo":"1055750653","befAcqSharesPer":"33.43","secVal":"1865163706","securitiesTypePost":"Equity Shares","afterAcqSharesNo":"1055750653","afterAcqSharesPer":"33.43","acqfromDt":"17-Feb-2020","acqtoDt":"17-Feb-2020","intimDt":"19-Feb-2020","acqMode":"Pledge Creation","derivativeType":"-","exchange":"NA","remarks":"-"},{"symbol":"MOTHERSUMI","company":"Motherson Sumi Systems Limited","anex":"7(2)","acqName":"Samvardhana Motherson International Ltd","date":"13-Dec-2019 13:20","pid":"1061834","tkdAcqm":null,"buyValue":"0","sellValue":"0","buyQuantity":"0","sellquantity":"0","secType":"Equity Shares","secAcq":"30200000","did":"262850","tdpTransactionType":"Pledge Revoke","tdpDerivativeContractType":"-","xbrl":"https://archives.nseindia.com/corporate/xbrl/IT_1061834_179611_13122019012033_WEB.xml","personCategory":"Promoters","befAcqSharesNo":"1055750653","befAcqSharesPer":"33.43","secVal":"4058880000","securitiesTypePost":"Equity Shares","afterAcqSharesNo":"1055750653","afterAcqSharesPer":"33.43","acqfromDt":"09-Dec-2019","acqtoDt":"09-Dec-2019","intimDt":"11-Dec-2019","acqMode":"Revokation of Pledge","derivativeType":"-","exchange":"NA","remarks":"-"},{"symbol":"MOTHERSUMI","company":"Motherson Sumi Systems Limited","anex":"7(2)","acqName":"Samvardhana Motherson International Ltd","date":"10-Dec-2019 19:21","pid":"1061553","tkdAcqm":null,"buyValue":"0","sellValue":"0","buyQuantity":"0","sellquantity":"0","secType":"Equity Shares","secAcq":"8266271","did":"262291","tdpTransactionType":"Pledge Revoke","tdpDerivativeContractType":"-","xbrl":"https://archives.nseindia.com/corporate/xbrl/IT_1061553_178934_10122019072115_WEB.xml","personCategory":"Promoters","befAcqSharesNo":"1055750653","befAcqSharesPer":"33.43","secVal":"1098174102","securitiesTypePost":"Equity Shares","afterAcqSharesNo":"1055750653","afterAcqSharesPer":"33.43","acqfromDt":"06-Dec-2019","acqtoDt":"06-Dec-2019","intimDt":"09-Dec-2019","acqMode":"Revokation of Pledge","derivativeType":"-","exchange":"NA","remarks":"-"},{"symbol":"MOTHERSUMI","company":"Motherson Sumi Systems Limited","anex":"7(2)","acqName":"Samvardhana Motherson International Ltd","date":"02-Dec-2019 18:48","pid":"1060766","tkdAcqm":null,"buyValue":"0","sellValue":"0","buyQuantity":"0","sellquantity":"0","secType":"Equity Shares","secAcq":"113816512","did":"260402","tdpTransactionType":"Pledge","tdpDerivativeContractType":"-","xbrl":"https://archives.nseindia.com/corporate/xbrl/IT_1060766_177068_02122019064842_WEB.xml","personCategory":"Promoters","befAcqSharesNo":"1055750653","befAcqSharesPer":"33.43","secVal":"15291248387","securitiesTypePost":"Equity Shares","afterAcqSharesNo":"1055750653","afterAcqSharesPer":"33.43","acqfromDt":"28-Nov-2019","acqtoDt":"28-Nov-2019","intimDt":"30-Nov-2019","acqMode":"Pledge Creation","derivativeType":"-","exchange":"NA","remarks":"-"},{"symbol":"MOTHERSUMI","company":"Motherson Sumi Systems Limited","anex":"7(2)","acqName":"Samvardhana Motherson International Ltd","date":"03-Sep-2019 18:14","pid":"1029827","tkdAcqm":null,"buyValue":"0","sellValue":"0","buyQuantity":"0","sellquantity":"0","secType":"Equity Shares","secAcq":"9370500","did":"153579","tdpTransactionType":"Pledge Revoke","tdpDerivativeContractType":"-","xbrl":"https://archives.nseindia.com/corporate/xbrl/IT_1029827_134972_03092019061435_WEB.xml","personCategory":"Promoters","befAcqSharesNo":"703833769","befAcqSharesPer":"33.43","secVal":"3548139825","securitiesTypePost":"Equity Shares","afterAcqSharesNo":"703833769","afterAcqSharesPer":"33.43","acqfromDt":"10-Jan-2018","acqtoDt":"10-Jan-2018","intimDt":"12-Jan-2018","acqMode":"Revokation of Pledge","derivativeType":"-","exchange":"NA","remarks":"-"},{"symbol":"MOTHERSUMI","company":"Motherson Sumi Systems Limited","anex":"7(2)","acqName":"Samvardhana Motherson International Ltd","date":"03-Aug-2019 19:16","pid":"1054899","tkdAcqm":null,"buyValue":"0","sellValue":"0","buyQuantity":"0","sellquantity":"0","secType":"Equity Shares","secAcq":"7000000","did":"244741","tdpTransactionType":"Pledge","tdpDerivativeContractType":"-","xbrl":"https://archives.nseindia.com/corporate/xbrl/IT_1054899_127770_03082019071615_WEB.xml","personCategory":"Promoters","befAcqSharesNo":"1055750653","befAcqSharesPer":"33.43","secVal":"747250000","securitiesTypePost":"Equity Shares","afterAcqSharesNo":"1055750653","afterAcqSharesPer":"33.43","acqfromDt":"31-Jul-2019","acqtoDt":"31-Jul-2019","intimDt":"01-Aug-2019","acqMode":"Pledge Creation","derivativeType":"-","exchange":"NA","remarks":"-"},{"symbol":"MOTHERSUMI","company":"Motherson Sumi Systems Limited","anex":"7(2)","acqName":"Samvardhana Motherson International Ltd","date":"03-Aug-2019 19:16","pid":"1054899","tkdAcqm":null,"buyValue":"0","sellValue":"0","buyQuantity":"0","sellquantity":"0","secType":"Equity Shares","secAcq":"4000000","did":"244742","tdpTransactionType":"Pledge","tdpDerivativeContractType":"-","xbrl":"https://archives.nseindia.com/corporate/xbrl/IT_1054899_127770_03082019071615_WEB.xml","personCategory":"Promoters","befAcqSharesNo":"1055750653","befAcqSharesPer":"33.43","secVal":"427000000","securitiesTypePost":"Equity Shares","afterAcqSharesNo":"1055750653","afterAcqSharesPer":"33.43","acqfromDt":"31-Jul-2019","acqtoDt":"31-Jul-2019","intimDt":"01-Aug-2019","acqMode":"Pledge Creation","derivativeType":"-","exchange":"NA","remarks":"-"},{"symbol":"MOTHERSUMI","company":"Motherson Sumi Systems Limited","anex":"7(2)","acqName":"Samvardhana Motherson International Ltd","date":"03-Aug-2019 19:16","pid":"1054899","tkdAcqm":null,"buyValue":"0","sellValue":"0","buyQuantity":"0","sellquantity":"0","secType":"Equity Shares","secAcq":"5000000","did":"244740","tdpTransactionType":"Pledge","tdpDerivativeContractType":"-","xbrl":"https://archives.nseindia.com/corporate/xbrl/IT_1054899_127770_03082019071615_WEB.xml","personCategory":"Promoters","befAcqSharesNo":"1055750653","befAcqSharesPer":"33.43","secVal":"533750000","securitiesTypePost":"Equity Shares","afterAcqSharesNo":"1055750653","afterAcqSharesPer":"33.43","acqfromDt":"31-Jul-2019","acqtoDt":"31-Jul-2019","intimDt":"01-Aug-2019","acqMode":"Pledge Creation","derivativeType":"-","exchange":"NA","remarks":"-"},{"symbol":"MOTHERSUMI","company":"Motherson Sumi Systems Limited","anex":"7(2)","acqName":"Samvardhana Motherson International Ltd","date":"20-May-2019 19:20","pid":"1052060","tkdAcqm":null,"buyValue":"0","sellValue":"0","buyQuantity":"0","sellquantity":"0","secType":"Equity Shares","secAcq":"5000000","did":"237071","tdpTransactionType":"Pledge","tdpDerivativeContractType":"-","xbrl":"https://archives.nseindia.com/corporate/xbrl/IT_1052060_103076_20052019072002_WEB.xml","personCategory":"Promoters","befAcqSharesNo":"1055750653","befAcqSharesPer":"33.43","secVal":"589750000","securitiesTypePost":"Equity Shares","afterAcqSharesNo":"1055750653","afterAcqSharesPer":"33.43","acqfromDt":"15-May-2019","acqtoDt":"15-May-2019","intimDt":"16-May-2019","acqMode":"Pledge Creation","derivativeType":"-","exchange":"NA","remarks":"-"},{"symbol":"MOTHERSUMI","company":"Motherson Sumi Systems Limited","anex":"7(2)","acqName":"Samvardhana Motherson International Ltd","date":"20-May-2019 19:20","pid":"1052060","tkdAcqm":null,"buyValue":"0","sellValue":"0","buyQuantity":"0","sellquantity":"0","secType":"Equity Shares","secAcq":"5600000","did":"237070","tdpTransactionType":"Pledge","tdpDerivativeContractType":"-","xbrl":"https://archives.nseindia.com/corporate/xbrl/IT_1052060_103076_20052019072002_WEB.xml","personCategory":"Promoters","befAcqSharesNo":"1055750653","befAcqSharesPer":"33.43","secVal":"660520000","securitiesTypePost":"Equity Shares","afterAcqSharesNo":"1055750653","afterAcqSharesPer":"33.43","acqfromDt":"15-May-2019","acqtoDt":"15-May-2019","intimDt":"16-May-2019","acqMode":"Pledge Creation","derivativeType":"-","exchange":"NA","remarks":"-"},{"symbol":"MOTHERSUMI","company":"Motherson Sumi Systems Limited","anex":"7(2)","acqName":"Samvardhana Motherson International Ltd","date":"20-May-2019 19:20","pid":"1052060","tkdAcqm":null,"buyValue":"0","sellValue":"0","buyQuantity":"0","sellquantity":"0","secType":"Equity Shares","secAcq":"4200000","did":"237069","tdpTransactionType":"Pledge","tdpDerivativeContractType":"-","xbrl":"https://archives.nseindia.com/corporate/xbrl/IT_1052060_103076_20052019072002_WEB.xml","personCategory":"Promoters","befAcqSharesNo":"1055750653","befAcqSharesPer":"33.43","secVal":"495390000","securitiesTypePost":"Equity Shares","afterAcqSharesNo":"1055750653","afterAcqSharesPer":"33.43","acqfromDt":"15-May-2019","acqtoDt":"15-May-2019","intimDt":"16-May-2019","acqMode":"Pledge Creation","derivativeType":"-","exchange":"NA","remarks":"-"},{"symbol":"MOTHERSUMI","company":"Motherson Sumi Systems Limited","anex":"7(2)","acqName":"Samvardhana Motherson International Ltd","date":"10-May-2019 18:43","pid":"1051838","tkdAcqm":null,"buyValue":"0","sellValue":"0","buyQuantity":"0","sellquantity":"0","secType":"Equity Shares","secAcq":"3000000","did":"236484","tdpTransactionType":"Pledge","tdpDerivativeContractType":"-","xbrl":"https://archives.nseindia.com/corporate/xbrl/IT_1051838_101372_10052019064301_WEB.xml","personCategory":"Promoters","befAcqSharesNo":"1055750653","befAcqSharesPer":"33.43","secVal":"400800000","securitiesTypePost":"Equity Shares","afterAcqSharesNo":"1055750653","afterAcqSharesPer":"33.43","acqfromDt":"06-May-2019","acqtoDt":"06-May-2019","intimDt":"08-May-2019","acqMode":"Pledge Creation","derivativeType":"-","exchange":"NA","remarks":"-"},{"symbol":"MOTHERSUMI","company":"Motherson Sumi Systems Limited","anex":"7(2)","acqName":"Samvardhana Motherson International Ltd","date":"10-May-2019 18:43","pid":"1051838","tkdAcqm":null,"buyValue":"0","sellValue":"0","buyQuantity":"0","sellquantity":"0","secType":"Equity Shares","secAcq":"1500000","did":"236485","tdpTransactionType":"Pledge Revoke","tdpDerivativeContractType":"-","xbrl":"https://archives.nseindia.com/corporate/xbrl/IT_1051838_101372_10052019064301_WEB.xml","personCategory":"Promoters","befAcqSharesNo":"1055750653","befAcqSharesPer":"33.43","secVal":"197475000","securitiesTypePost":"Equity Shares","afterAcqSharesNo":"1055750653","afterAcqSharesPer":"33.43","acqfromDt":"07-May-2019","acqtoDt":"07-May-2019","intimDt":"09-May-2019","acqMode":"Revokation of Pledge","derivativeType":"-","exchange":"NA","remarks":"-"},{"symbol":"MOTHERSUMI","company":"Motherson Sumi Systems Limited","anex":"7(2)","acqName":"Samvardhana Motherson International Ltd","date":"14-Mar-2019 20:34","pid":"1050109","tkdAcqm":null,"buyValue":"0","sellValue":"0","buyQuantity":"0","sellquantity":"0","secType":"Equity Shares","secAcq":"5000000","did":"229150","tdpTransactionType":"Pledge","tdpDerivativeContractType":"-","xbrl":"https://archives.nseindia.com/corporate/xbrl/IT_1050109_85392_14032019083447_WEB.xml","personCategory":"Promoters","befAcqSharesNo":"1055750653","befAcqSharesPer":"33.43","secVal":"840250000","securitiesTypePost":"Equity Shares","afterAcqSharesNo":"1055750653","afterAcqSharesPer":"33.43","acqfromDt":"12-Mar-2019","acqtoDt":"12-Mar-2019","intimDt":"13-Mar-2019","acqMode":"Pledge Creation","derivativeType":"-","exchange":"NA","remarks":"-"},{"symbol":"MOTHERSUMI","company":"Motherson Sumi Systems Limited","anex":"7(2)","acqName":"Samvardhana Motherson International Ltd","date":"14-Mar-2019 20:34","pid":"1050109","tkdAcqm":null,"buyValue":"0","sellValue":"0","buyQuantity":"0","sellquantity":"0","secType":"Equity Shares","secAcq":"8000000","did":"229151","tdpTransactionType":"Pledge Revoke","tdpDerivativeContractType":"-","xbrl":"https://archives.nseindia.com/corporate/xbrl/IT_1050109_85392_14032019083447_WEB.xml","personCategory":"Promoters","befAcqSharesNo":"1055750653","befAcqSharesPer":"33.43","secVal":"1344400000","securitiesTypePost":"Equity Shares","afterAcqSharesNo":"1055750653","afterAcqSharesPer":"33.43","acqfromDt":"12-Mar-2019","acqtoDt":"12-Mar-2019","intimDt":"13-Mar-2019","acqMode":"Revokation of Pledge","derivativeType":"-","exchange":"NA","remarks":"-"},{"symbol":"MOTHERSUMI","company":"Motherson Sumi Systems Limited","anex":"7(2)","acqName":"Samvardhana Motherson International Ltd","date":"01-Mar-2019 15:47","pid":"1049413","tkdAcqm":null,"buyValue":"0","sellValue":"0","buyQuantity":"0","sellquantity":"0","secType":"Equity Shares","secAcq":"7500000","did":"226282","tdpTransactionType":"Pledge","tdpDerivativeContractType":"-","xbrl":"https://archives.nseindia.com/corporate/xbrl/IT_1049413_84521_01032019034737_WEB.xml","personCategory":"Promoters","befAcqSharesNo":"1055750653","befAcqSharesPer":"33.43","secVal":"1219500000","securitiesTypePost":"Equity Shares","afterAcqSharesNo":"1055750653","afterAcqSharesPer":"33.43","acqfromDt":"28-Feb-2019","acqtoDt":"28-Feb-2019","intimDt":"01-Mar-2019","acqMode":"Revokation of Pledge","derivativeType":"-","exchange":"NA","remarks":"-"},{"symbol":"MOTHERSUMI","company":"Motherson Sumi Systems Limited","anex":"7(2)","acqName":"Samvardhana Motherson International Ltd","date":"25-Feb-2019 19:05","pid":"1049117","tkdAcqm":null,"buyValue":"0","sellValue":"0","buyQuantity":"0","sellquantity":"0","secType":"Equity Shares","secAcq":"7500000","did":"225426","tdpTransactionType":"Pledge","tdpDerivativeContractType":"-","xbrl":"https://archives.nseindia.com/corporate/xbrl/IT_1049117_84170_25022019070520_WEB.xml","personCategory":"Promoters","befAcqSharesNo":"1055750653","befAcqSharesPer":"33.43","secVal":"1018125000","securitiesTypePost":"Equity Shares","afterAcqSharesNo":"1055750653","afterAcqSharesPer":"33.43","acqfromDt":"21-Feb-2019","acqtoDt":"21-Feb-2019","intimDt":"23-Feb-2019","acqMode":"Revokation of Pledge","derivativeType":"-","exchange":"NA","remarks":"-"},{"symbol":"MOTHERSUMI","company":"Motherson Sumi Systems Limited","anex":"7(2)","acqName":"Samvardhana Motherson International Ltd","date":"25-Feb-2019 17:46","pid":"1049100","tkdAcqm":null,"buyValue":"0","sellValue":"0","buyQuantity":"0","sellquantity":"0","secType":"Equity Shares","secAcq":"17000000","did":"225389","tdpTransactionType":"Pledge","tdpDerivativeContractType":"-","xbrl":"https://archives.nseindia.com/corporate/xbrl/IT_1049100_84156_25022019054653_WEB.xml","personCategory":"Promoters","befAcqSharesNo":"1055750653","befAcqSharesPer":"33.43","secVal":"2204900000","securitiesTypePost":"Equity Shares","afterAcqSharesNo":"1055750653","afterAcqSharesPer":"33.43","acqfromDt":"18-Feb-2019","acqtoDt":"18-Feb-2019","intimDt":"21-Feb-2019","acqMode":"Pledge Creation","derivativeType":"-","exchange":"NA","remarks":"-"},{"symbol":"MOTHERSUMI","company":"Motherson Sumi Systems Limited","anex":"7(2)","acqName":"Samvardhana Motherson International Ltd","date":"15-Feb-2019 13:43","pid":"1048542","tkdAcqm":null,"buyValue":"0","sellValue":"0","buyQuantity":"0","sellquantity":"0","secType":"Equity Shares","secAcq":"2500000","did":"223656","tdpTransactionType":"Pledge","tdpDerivativeContractType":"-","xbrl":"https://archives.nseindia.com/corporate/xbrl/IT_1048542_83322_15022019014316_WEB.xml","personCategory":"Promoters","befAcqSharesNo":"1055750653","befAcqSharesPer":"33.43","secVal":"331750000","securitiesTypePost":"Equity Shares","afterAcqSharesNo":"1055750653","afterAcqSharesPer":"33.43","acqfromDt":"11-Feb-2019","acqtoDt":"11-Feb-2019","intimDt":"13-Feb-2019","acqMode":"Pledge Creation","derivativeType":"-","exchange":"NA","remarks":"-"},{"symbol":"MOTHERSUMI","company":"Motherson Sumi Systems Limited","anex":"7(2)","acqName":"Samvardhana Motherson International Ltd","date":"02-Jan-2019 17:04","pid":"1046855","tkdAcqm":null,"buyValue":"0","sellValue":"0","buyQuantity":"0","sellquantity":"0","secType":"Equity Shares","secAcq":"64500000","did":"218911","tdpTransactionType":"Pledge Revoke","tdpDerivativeContractType":"-","xbrl":"https://archives.nseindia.com/corporate/xbrl/IT_1046855_64013_02012019050429_WEB.xml","personCategory":"Promoters","befAcqSharesNo":"1055750653","befAcqSharesPer":"33.43","secVal":"10478025000","securitiesTypePost":"Equity Shares","afterAcqSharesNo":"1055750653","afterAcqSharesPer":"33.43","acqfromDt":"27-Dec-2018","acqtoDt":"27-Dec-2018","intimDt":"31-Dec-2018","acqMode":"Revokation of Pledge","derivativeType":"-","exchange":"NA","remarks":"-"},{"symbol":"MOTHERSUMI","company":"Motherson Sumi Systems Limited","anex":"7(2)","acqName":"Samvardhana Motherson International Ltd","date":"26-Dec-2018 16:14","pid":"1046568","tkdAcqm":null,"buyValue":"0","sellValue":"0","buyQuantity":"0","sellquantity":"0","secType":"Equity Shares","secAcq":"13500000","did":"217648","tdpTransactionType":"Pledge","tdpDerivativeContractType":"-","xbrl":"https://archives.nseindia.com/corporate/xbrl/IT_1046568_63571_26122018041408_WEB.xml","personCategory":"Promoters","befAcqSharesNo":"1055750653","befAcqSharesPer":"33.43","secVal":"2322675000","securitiesTypePost":"Equity Shares","afterAcqSharesNo":"1055750653","afterAcqSharesPer":"33.43","acqfromDt":"19-Dec-2018","acqtoDt":"19-Dec-2018","intimDt":"21-Dec-2018","acqMode":"Pledge Creation","derivativeType":"-","exchange":"NA","remarks":"-"},{"symbol":"MOTHERSUMI","company":"Motherson Sumi Systems Limited","anex":"7(2)","acqName":"Samvardhana Motherson International Ltd","date":"08-Dec-2018 14:41","pid":"1045736","tkdAcqm":null,"buyValue":"0","sellValue":"0","buyQuantity":"0","sellquantity":"0","secType":"Equity Shares","secAcq":"7000000","did":"214529","tdpTransactionType":"Pledge","tdpDerivativeContractType":"-","xbrl":null,"personCategory":"Promoters","befAcqSharesNo":"1055750653","befAcqSharesPer":"33.43","secVal":"1102850000","securitiesTypePost":"Equity Shares","afterAcqSharesNo":"1055750653","afterAcqSharesPer":"33.43","acqfromDt":"05-Dec-2018","acqtoDt":"05-Dec-2018","intimDt":"07-Dec-2018","acqMode":"Pledge Creation","derivativeType":"-","exchange":"NA","remarks":"-"},{"symbol":"MOTHERSUMI","company":"Motherson Sumi Systems Limited","anex":"7(2)","acqName":"Samvardhana Motherson International Ltd","date":"08-Dec-2018 14:41","pid":"1045736","tkdAcqm":null,"buyValue":"0","sellValue":"0","buyQuantity":"0","sellquantity":"0","secType":"Equity Shares","secAcq":"21000000","did":"214530","tdpTransactionType":"Pledge","tdpDerivativeContractType":"-","xbrl":null,"personCategory":"Promoters","befAcqSharesNo":"1055750653","befAcqSharesPer":"33.43","secVal":"3304350000","securitiesTypePost":"Equity Shares","afterAcqSharesNo":"1055750653","afterAcqSharesPer":"33.43","acqfromDt":"06-Dec-2018","acqtoDt":"06-Dec-2018","intimDt":"07-Dec-2018","acqMode":"Pledge Creation","derivativeType":"-","exchange":"NA","remarks":"-"},{"symbol":"MOTHERSUMI","company":"Motherson Sumi Systems Limited","anex":"7(2)","acqName":"Samvardhana Motherson International Ltd","date":"08-Dec-2018 14:41","pid":"1045736","tkdAcqm":null,"buyValue":"0","sellValue":"0","buyQuantity":"0","sellquantity":"0","secType":"Equity Shares","secAcq":"28000000","did":"214531","tdpTransactionType":"Pledge","tdpDerivativeContractType":"-","xbrl":null,"personCategory":"Promoters","befAcqSharesNo":"1055750653","befAcqSharesPer":"33.43","secVal":"4405800000","securitiesTypePost":"Equity Shares","afterAcqSharesNo":"1055750653","afterAcqSharesPer":"33.43","acqfromDt":"06-Dec-2018","acqtoDt":"06-Dec-2018","intimDt":"07-Dec-2018","acqMode":"Pledge Creation","derivativeType":"-","exchange":"NA","remarks":"-"},{"symbol":"MOTHERSUMI","company":"Motherson Sumi Systems Limited","anex":"7(2)","acqName":"Samvardhana Motherson International Ltd","date":"16-Nov-2018 17:50","pid":"1044702","tkdAcqm":null,"buyValue":"0","sellValue":"0","buyQuantity":"0","sellquantity":"0","secType":"Equity Shares","secAcq":"19650000","did":"207276","tdpTransactionType":"Pledge Revoke","tdpDerivativeContractType":"-","xbrl":"https://archives.nseindia.com/corporate/xbrl/IT_1044702_61112_16112018055010_WEB.xml","personCategory":"Promoters","befAcqSharesNo":"1055750653","befAcqSharesPer":"33.43","secVal":"3223582500","securitiesTypePost":"Equity Shares","afterAcqSharesNo":"1055750653","afterAcqSharesPer":"33.43","acqfromDt":"12-Nov-2018","acqtoDt":"12-Nov-2018","intimDt":"14-Nov-2018","acqMode":"Revokation of Pledge","derivativeType":"-","exchange":"NA","remarks":"-"},{"symbol":"MOTHERSUMI","company":"Motherson Sumi Systems Limited","anex":"7(2)","acqName":"Samvardhana Motherson International Ltd","date":"13-Nov-2018 20:27","pid":"1044562","tkdAcqm":null,"buyValue":"0","sellValue":"0","buyQuantity":"0","sellquantity":"0","secType":"Equity Shares","secAcq":"28050000","did":"206599","tdpTransactionType":"Pledge","tdpDerivativeContractType":"-","xbrl":"https://archives.nseindia.com/corporate/xbrl/IT_1044562_59231_13112018082709_WEB.xml","personCategory":"Promoters","befAcqSharesNo":"1055750653","befAcqSharesPer":"33.43","secVal":"4774110000","securitiesTypePost":"Equity Shares","afterAcqSharesNo":"1055750653","afterAcqSharesPer":"33.43","acqfromDt":"06-Nov-2018","acqtoDt":"06-Nov-2018","intimDt":"06-Nov-2018","acqMode":"Pledge Creation","derivativeType":"-","exchange":"NA","remarks":"-"},{"symbol":"MOTHERSUMI","company":"Motherson Sumi Systems Limited","anex":"7(2)","acqName":"GEETA SONI","date":"13-Nov-2018 20:17","pid":"1044561","tkdAcqm":null,"buyValue":"0","sellValue":"0","buyQuantity":"0","sellquantity":"0","secType":"Equity Shares","secAcq":"2870109","did":"206592","tdpTransactionType":"Buy","tdpDerivativeContractType":"-","xbrl":"https://archives.nseindia.com/corporate/xbrl/IT_1044561_59226_13112018081728_WEB.xml","personCategory":"Immediate relative","befAcqSharesNo":"5740219","befAcqSharesPer":"0.27","secVal":"498107417","securitiesTypePost":"Equity Shares","afterAcqSharesNo":"8610328","afterAcqSharesPer":"0.27","acqfromDt":"01-Nov-2018","acqtoDt":"01-Nov-2018","intimDt":"06-Nov-2018","acqMode":"Bonus","derivativeType":"-","exchange":"NA","remarks":"-"},{"symbol":"MOTHERSUMI","company":"Motherson Sumi Systems Limited","anex":"7(2)","acqName":"ALOK GOEL","date":"13-Nov-2018 20:17","pid":"1044561","tkdAcqm":null,"buyValue":"0","sellValue":"0","buyQuantity":"0","sellquantity":"0","secType":"Equity Shares","secAcq":"25","did":"206598","tdpTransactionType":"Buy","tdpDerivativeContractType":"-","xbrl":"https://archives.nseindia.com/corporate/xbrl/IT_1044561_59226_13112018081728_WEB.xml","personCategory":"Key Managerial Personnel","befAcqSharesNo":"50","befAcqSharesPer":"0","secVal":"4383.25","securitiesTypePost":"Equity Shares","afterAcqSharesNo":"75","afterAcqSharesPer":"0.00","acqfromDt":"01-Nov-2018","acqtoDt":"01-Nov-2018","intimDt":"06-Nov-2018","acqMode":"Bonus","derivativeType":"-","exchange":"NA","remarks":"-"},{"symbol":"MOTHERSUMI","company":"Motherson Sumi Systems Limited","anex":"7(2)","acqName":"G.N. GAUBA","date":"13-Nov-2018 20:17","pid":"1044561","tkdAcqm":null,"buyValue":"0","sellValue":"0","buyQuantity":"0","sellquantity":"0","secType":"Equity Shares","secAcq":"12150","did":"206597","tdpTransactionType":"Buy","tdpDerivativeContractType":"-","xbrl":"https://archives.nseindia.com/corporate/xbrl/IT_1044561_59226_13112018081728_WEB.xml","personCategory":"Key Managerial Personnel","befAcqSharesNo":"24300","befAcqSharesPer":"0","secVal":"2108632.5","securitiesTypePost":"Equity Shares","afterAcqSharesNo":"36450","afterAcqSharesPer":"0.00","acqfromDt":"01-Nov-2018","acqtoDt":"01-Nov-2018","intimDt":"06-Nov-2018","acqMode":"Bonus","derivativeType":"-","exchange":"NA","remarks":"-"},{"symbol":"MOTHERSUMI","company":"Motherson Sumi Systems Limited","anex":"7(2)","acqName":"Samvardhana Motherson International Ltd","date":"13-Nov-2018 20:17","pid":"1044561","tkdAcqm":null,"buyValue":"0","sellValue":"0","buyQuantity":"0","sellquantity":"0","secType":"Equity Shares","secAcq":"351916884","did":"206586","tdpTransactionType":"Buy","tdpDerivativeContractType":"-","xbrl":"https://archives.nseindia.com/corporate/xbrl/IT_1044561_59226_13112018081728_WEB.xml","personCategory":"Promoters","befAcqSharesNo":"703833769","befAcqSharesPer":"33.43","secVal":"61075175218","securitiesTypePost":"Equity Shares","afterAcqSharesNo":"1055750653","afterAcqSharesPer":"33.43","acqfromDt":"01-Nov-2018","acqtoDt":"01-Nov-2018","intimDt":"06-Nov-2018","acqMode":"Bonus","derivativeType":"-","exchange":"NA","remarks":"-"},{"symbol":"MOTHERSUMI","company":"Motherson Sumi Systems Limited","anex":"7(2)","acqName":"PANKAJ MITAL","date":"13-Nov-2018 20:17","pid":"1044561","tkdAcqm":null,"buyValue":"0","sellValue":"0","buyQuantity":"0","sellquantity":"0","secType":"Equity Shares","secAcq":"33091","did":"206596","tdpTransactionType":"Buy","tdpDerivativeContractType":"-","xbrl":"https://archives.nseindia.com/corporate/xbrl/IT_1044561_59226_13112018081728_WEB.xml","personCategory":"Key Managerial Personnel","befAcqSharesNo":"66182","befAcqSharesPer":"0","secVal":"5801845.03","securitiesTypePost":"Equity Shares","afterAcqSharesNo":"99273","afterAcqSharesPer":"0.00","acqfromDt":"01-Nov-2018","acqtoDt":"01-Nov-2018","intimDt":"06-Nov-2018","acqMode":"Bonus","derivativeType":"-","exchange":"NA","remarks":"-"},{"symbol":"MOTHERSUMI","company":"Motherson Sumi Systems Limited","anex":"7(2)","acqName":"NAVEEN GANZU","date":"13-Nov-2018 20:17","pid":"1044561","tkdAcqm":null,"buyValue":"0","sellValue":"0","buyQuantity":"0","sellquantity":"0","secType":"Equity Shares","secAcq":"70650","did":"206595","tdpTransactionType":"Buy","tdpDerivativeContractType":"-","xbrl":"https://archives.nseindia.com/corporate/xbrl/IT_1044561_59226_13112018081728_WEB.xml","personCategory":"Director","befAcqSharesNo":"141301","befAcqSharesPer":"0","secVal":"12261307.5","securitiesTypePost":"Equity Shares","afterAcqSharesNo":"211951","afterAcqSharesPer":"0.00","acqfromDt":"01-Nov-2018","acqtoDt":"01-Nov-2018","intimDt":"06-Nov-2018","acqMode":"Bonus","derivativeType":"-","exchange":"NA","remarks":"-"},{"symbol":"MOTHERSUMI","company":"Motherson Sumi Systems Limited","anex":"7(2)","acqName":"GEETA MATHUR","date":"13-Nov-2018 20:17","pid":"1044561","tkdAcqm":null,"buyValue":"0","sellValue":"0","buyQuantity":"0","sellquantity":"0","secType":"Equity Shares","secAcq":"3375","did":"206594","tdpTransactionType":"Buy","tdpDerivativeContractType":"-","xbrl":"https://archives.nseindia.com/corporate/xbrl/IT_1044561_59226_13112018081728_WEB.xml","personCategory":"Director","befAcqSharesNo":"6750","befAcqSharesPer":"0","secVal":"585731.25","securitiesTypePost":"Equity Shares","afterAcqSharesNo":"10125","afterAcqSharesPer":"0.00","acqfromDt":"01-Nov-2018","acqtoDt":"01-Nov-2018","intimDt":"06-Nov-2018","acqMode":"Bonus","derivativeType":"-","exchange":"NA","remarks":"-"},{"symbol":"MOTHERSUMI","company":"Motherson Sumi Systems Limited","anex":"7(2)","acqName":"Arjun Puri","date":"13-Nov-2018 20:17","pid":"1044561","tkdAcqm":null,"buyValue":"0","sellValue":"0","buyQuantity":"0","sellquantity":"0","secType":"Equity Shares","secAcq":"1250","did":"206593","tdpTransactionType":"Buy","tdpDerivativeContractType":"-","xbrl":"https://archives.nseindia.com/corporate/xbrl/IT_1044561_59226_13112018081728_WEB.xml","personCategory":"Director","befAcqSharesNo":"2500","befAcqSharesPer":"0","secVal":"216937.5","securitiesTypePost":"Equity Shares","afterAcqSharesNo":"3750","afterAcqSharesPer":"0.00","acqfromDt":"01-Nov-2018","acqtoDt":"01-Nov-2018","intimDt":"06-Nov-2018","acqMode":"Bonus","derivativeType":"-","exchange":"NA","remarks":"-"},{"symbol":"MOTHERSUMI","company":"Motherson Sumi Systems Limited","anex":"7(2)","acqName":"NILU MEHRA","date":"13-Nov-2018 20:17","pid":"1044561","tkdAcqm":null,"buyValue":"0","sellValue":"0","buyQuantity":"0","sellquantity":"0","secType":"Equity Shares","secAcq":"2623230","did":"206591","tdpTransactionType":"Buy","tdpDerivativeContractType":"-","xbrl":"https://archives.nseindia.com/corporate/xbrl/IT_1044561_59226_13112018081728_WEB.xml","personCategory":"Immediate relative","befAcqSharesNo":"5246460","befAcqSharesPer":"0.25","secVal":"455261566.5","securitiesTypePost":"Equity Shares","afterAcqSharesNo":"7869690","afterAcqSharesPer":"0.25","acqfromDt":"01-Nov-2018","acqtoDt":"01-Nov-2018","intimDt":"06-Nov-2018","acqMode":"Bonus","derivativeType":"-","exchange":"NA","remarks":"-"},{"symbol":"MOTHERSUMI","company":"Motherson Sumi Systems Limited","anex":"7(2)","acqName":"LAKSH VAAMAN SEHGAL","date":"13-Nov-2018 20:17","pid":"1044561","tkdAcqm":null,"buyValue":"0","sellValue":"0","buyQuantity":"0","sellquantity":"0","secType":"Equity Shares","secAcq":"41","did":"206590","tdpTransactionType":"Buy","tdpDerivativeContractType":"-","xbrl":"https://archives.nseindia.com/corporate/xbrl/IT_1044561_59226_13112018081728_WEB.xml","personCategory":"Promoters","befAcqSharesNo":"82","befAcqSharesPer":"0","secVal":"7115.55","securitiesTypePost":"Equity Shares","afterAcqSharesNo":"123","afterAcqSharesPer":"0.00","acqfromDt":"01-Nov-2018","acqtoDt":"01-Nov-2018","intimDt":"06-Nov-2018","acqMode":"Bonus","derivativeType":"-","exchange":"NA","remarks":"-"},{"symbol":"MOTHERSUMI","company":"Motherson Sumi Systems Limited","anex":"7(2)","acqName":"RENU ALKA SEHGAL","date":"13-Nov-2018 20:17","pid":"1044561","tkdAcqm":null,"buyValue":"0","sellValue":"0","buyQuantity":"0","sellquantity":"0","secType":"Equity Shares","secAcq":"50028","did":"206589","tdpTransactionType":"Buy","tdpDerivativeContractType":"-","xbrl":"https://archives.nseindia.com/corporate/xbrl/IT_1044561_59226_13112018081728_WEB.xml","personCategory":"Immediate relative","befAcqSharesNo":"100057","befAcqSharesPer":"0","secVal":"8682359.4","securitiesTypePost":"Equity Shares","afterAcqSharesNo":"150085","afterAcqSharesPer":"0.00","acqfromDt":"01-Nov-2018","acqtoDt":"01-Nov-2018","intimDt":"06-Nov-2018","acqMode":"Bonus","derivativeType":"-","exchange":"NA","remarks":"-"},{"symbol":"MOTHERSUMI","company":"Motherson Sumi Systems Limited","anex":"7(2)","acqName":"VIVEK CHAAND SEHGAL","date":"13-Nov-2018 20:17","pid":"1044561","tkdAcqm":null,"buyValue":"0","sellValue":"0","buyQuantity":"0","sellquantity":"0","secType":"Equity Shares","secAcq":"24388467","did":"206588","tdpTransactionType":"Buy","tdpDerivativeContractType":"-","xbrl":"https://archives.nseindia.com/corporate/xbrl/IT_1044561_59226_13112018081728_WEB.xml","personCategory":"Promoters","befAcqSharesNo":"48776935","befAcqSharesPer":"2.32","secVal":"4232618448","securitiesTypePost":"Equity Shares","afterAcqSharesNo":"73165402","afterAcqSharesPer":"2.32","acqfromDt":"01-Nov-2018","acqtoDt":"01-Nov-2018","intimDt":"06-Nov-2018","acqMode":"Bonus","derivativeType":"-","exchange":"NA","remarks":"-"},{"symbol":"MOTHERSUMI","company":"Motherson Sumi Systems Limited","anex":"7(2)","acqName":"RADHA RANI HOLDINGS PTE LIMITED","date":"13-Nov-2018 20:17","pid":"1044561","tkdAcqm":null,"buyValue":"0","sellValue":"0","buyQuantity":"0","sellquantity":"0","secType":"Equity Shares","secAcq":"1147541","did":"206587","tdpTransactionType":"Buy","tdpDerivativeContractType":"-","xbrl":"https://archives.nseindia.com/corporate/xbrl/IT_1044561_59226_13112018081728_WEB.xml","personCategory":"Promoters","befAcqSharesNo":"2295082","befAcqSharesPer":"0.11","secVal":"199155740.6","securitiesTypePost":"Equity Shares","afterAcqSharesNo":"3442623","afterAcqSharesPer":"0.11","acqfromDt":"01-Nov-2018","acqtoDt":"01-Nov-2018","intimDt":"06-Nov-2018","acqMode":"Bonus","derivativeType":"-","exchange":"NA","remarks":"-"},{"symbol":"MOTHERSUMI","company":"Motherson Sumi Systems Limited","anex":"7(2)","acqName":"Samvardhana Motherson International Ltd","date":"02-Nov-2018 17:24","pid":"1044270","tkdAcqm":null,"buyValue":"0","sellValue":"0","buyQuantity":"0","sellquantity":"0","secType":"Equity Shares","secAcq":"1500000","did":"205501","tdpTransactionType":"Pledge","tdpDerivativeContractType":"-","xbrl":"https://archives.nseindia.com/corporate/xbrl/IT_1044270_57334_02112018052414_WEB.xml","personCategory":"Promoters","befAcqSharesNo":"703833769","befAcqSharesPer":"33.43","secVal":"342750000","securitiesTypePost":"Equity Shares","afterAcqSharesNo":"703833769","afterAcqSharesPer":"33.43","acqfromDt":"29-Oct-2018","acqtoDt":"29-Oct-2018","intimDt":"31-Oct-2018","acqMode":"Pledge Creation","derivativeType":"-","exchange":"BSE,NSE","remarks":"-"},{"symbol":"MOTHERSUMI","company":"Motherson Sumi Systems Limited","anex":"7(2)","acqName":"SaSamvardhana Motherson International Ltd","date":"28-Sep-2018 20:55","pid":"1042659","tkdAcqm":null,"buyValue":"0","sellValue":"0","buyQuantity":"0","sellquantity":"0","secType":"Equity Shares","secAcq":"10900000","did":"201371","tdpTransactionType":"Pledge","tdpDerivativeContractType":"-","xbrl":"https://archives.nseindia.com/corporate/xbrl/IT_1042659_40426_28092018085513_WEB.xml","personCategory":"Promoters","befAcqSharesNo":"703833769","befAcqSharesPer":"33.43","secVal":"2771325000","securitiesTypePost":"Equity Shares","afterAcqSharesNo":"703833769","afterAcqSharesPer":"33.43","acqfromDt":"24-Sep-2018","acqtoDt":"24-Sep-2018","intimDt":"26-Sep-2018","acqMode":"Pledge Creation","derivativeType":"-","exchange":"NA","remarks":"-"},{"symbol":"MOTHERSUMI","company":"Motherson Sumi Systems Limited","anex":"7(2)","acqName":"SaSamvardhana Motherson International Ltd","date":"09-Jul-2018 22:04","pid":"1038411","tkdAcqm":null,"buyValue":"0","sellValue":"0","buyQuantity":"0","sellquantity":"0","secType":"Equity Shares","secAcq":"29500","did":"182654","tdpTransactionType":"Pledge Revoke","tdpDerivativeContractType":"-","xbrl":"https://archives.nseindia.com/corporate/xbrl/IT_1038411_18955_09072018100453_WEB.xml","personCategory":"Promoters","befAcqSharesNo":"703833769","befAcqSharesPer":"33.43","secVal":"8717250","securitiesTypePost":"Equity Shares","afterAcqSharesNo":"703833769","afterAcqSharesPer":"33.43","acqfromDt":"04-Jul-2018","acqtoDt":"04-Jul-2018","intimDt":"06-Jul-2018","acqMode":"Revokation of Pledge","derivativeType":"-","exchange":"NA","remarks":"-"},{"symbol":"MOTHERSUMI","company":"Motherson Sumi Systems Limited","anex":"7(2)","acqName":"SaSamvardhana Motherson International Ltd","date":"03-Jul-2018 20:27","pid":"1038031","tkdAcqm":null,"buyValue":"0","sellValue":"0","buyQuantity":"0","sellquantity":"0","secType":"Equity Shares","secAcq":"1400000","did":"182006","tdpTransactionType":"Pledge","tdpDerivativeContractType":"-","xbrl":"https://archives.nseindia.com/corporate/xbrl/IT_1038031_16807_03072018082720_WEB.xml","personCategory":"Promoters","befAcqSharesNo":"703833769","befAcqSharesPer":"33.43","secVal":"387730000","securitiesTypePost":"Equity Shares","afterAcqSharesNo":"703833769","afterAcqSharesPer":"33.43","acqfromDt":"27-Jun-2018","acqtoDt":"27-Jun-2018","intimDt":"29-Jun-2018","acqMode":"Pledge Creation","derivativeType":"-","exchange":"NA","remarks":"-"},{"symbol":"MOTHERSUMI","company":"Motherson Sumi Systems Limited","anex":"7(2)","acqName":"SaSamvardhana Motherson International Ltd","date":"07-Jun-2018 19:31","pid":"1036493","tkdAcqm":null,"buyValue":"0","sellValue":"0","buyQuantity":"0","sellquantity":"0","secType":"Equity Shares","secAcq":"2500000","did":"177043","tdpTransactionType":"Pledge","tdpDerivativeContractType":"-","xbrl":null,"personCategory":"Promoters","befAcqSharesNo":"766375000","befAcqSharesPer":"33.43","secVal":"766375000","securitiesTypePost":"Equity Shares","afterAcqSharesNo":"766375000","afterAcqSharesPer":"33.43","acqfromDt":"04-Jun-2018","acqtoDt":"04-Jun-2018","intimDt":"05-Jun-2018","acqMode":"Pledge Creation","derivativeType":"-","exchange":"NA","remarks":"-"},{"symbol":"MOTHERSUMI","company":"Motherson Sumi Systems Limited","anex":"7(2)","acqName":"SaSamvardhana Motherson International Ltd","date":"29-May-2018 18:37","pid":"1035949","tkdAcqm":null,"buyValue":"0","sellValue":"0","buyQuantity":"0","sellquantity":"0","secType":"Equity Shares","secAcq":"2500000","did":"174359","tdpTransactionType":"Pledge","tdpDerivativeContractType":"-","xbrl":"https://archives.nseindia.com/corporate/xbrl/IT_1035949_12701_29052018063759_WEB.xml","personCategory":"Promoters","befAcqSharesNo":"703833769","befAcqSharesPer":"33.43","secVal":"754000000","securitiesTypePost":"Equity Shares","afterAcqSharesNo":"703833769","afterAcqSharesPer":"33.43","acqfromDt":"24-May-2018","acqtoDt":"24-May-2018","intimDt":"25-May-2018","acqMode":"Pledge Creation","derivativeType":"-","exchange":"NA","remarks":"-"},{"symbol":"MOTHERSUMI","company":"Motherson Sumi Systems Limited","anex":"7(2)","acqName":"Samvardhana Motherson International Ltd","date":"24-Feb-2018 13:01","pid":"1031324","tkdAcqm":null,"buyValue":"0","sellValue":"0","buyQuantity":"0","sellquantity":"0","secType":"Equity Shares","secAcq":"1200000","did":"159858","tdpTransactionType":"Pledge","tdpDerivativeContractType":"-","xbrl":null,"personCategory":"Promoters","befAcqSharesNo":"703833769","befAcqSharesPer":"33.43","secVal":"372780000","securitiesTypePost":"Equity Shares","afterAcqSharesNo":"703833769","afterAcqSharesPer":"33.43","acqfromDt":"22-Feb-2018","acqtoDt":"22-Feb-2018","intimDt":"23-Feb-2018","acqMode":"Pledge Creation","derivativeType":"-","exchange":"NA","remarks":"-"},{"symbol":"MOTHERSUMI","company":"Motherson Sumi Systems Limited","anex":"7(2)","acqName":"Samvardhana Motherson International Ltd","date":"13-Feb-2018 16:12","pid":"1030775","tkdAcqm":null,"buyValue":"0","sellValue":"0","buyQuantity":"0","sellquantity":"0","secType":"Equity Shares","secAcq":"12500000","did":"157648","tdpTransactionType":"Pledge Revoke","tdpDerivativeContractType":"-","xbrl":null,"personCategory":"Promoters","befAcqSharesNo":"703833769","befAcqSharesPer":"33.43","secVal":"4550000000","securitiesTypePost":"Equity Shares","afterAcqSharesNo":"703833769","afterAcqSharesPer":"33.43","acqfromDt":"08-Feb-2018","acqtoDt":"08-Feb-2018","intimDt":"10-Feb-2018","acqMode":"Revokation of Pledge","derivativeType":"-","exchange":"NA","remarks":"-"},{"symbol":"MOTHERSUMI","company":"Motherson Sumi Systems Limited","anex":"7(2)","acqName":"Samvardhana Motherson International Ltd","date":"17-Jan-2018 19:45","pid":"1029830","tkdAcqm":null,"buyValue":"0","sellValue":"0","buyQuantity":"0","sellquantity":"0","secType":"Equity Shares","secAcq":"9370500","did":"153583","tdpTransactionType":"Pledge Revoke","tdpDerivativeContractType":"-","xbrl":null,"personCategory":"Promoters","befAcqSharesNo":"703833769","befAcqSharesPer":"33.43","secVal":"3548139825","securitiesTypePost":"Equity Shares","afterAcqSharesNo":"703833769","afterAcqSharesPer":"33.43","acqfromDt":"10-Jan-2018","acqtoDt":"10-Jan-2018","intimDt":"12-Jan-2018","acqMode":"Revokation of Pledge","derivativeType":"-","exchange":"NA","remarks":"-"},{"symbol":"MOTHERSUMI","company":null,"anex":"7(2)","acqName":"Arjun Puri","date":"26-Dec-2017 19:52","pid":"1028799","tkdAcqm":null,"buyValue":"0","sellValue":"0","buyQuantity":"0","sellquantity":"0","secType":"Equity Shares","secAcq":"2500","did":"150418","tdpTransactionType":"Buy","tdpDerivativeContractType":"-","xbrl":null,"personCategory":"Director","befAcqSharesNo":"Nil","befAcqSharesPer":"0","secVal":"986275","securitiesTypePost":"Equity Shares","afterAcqSharesNo":"2500","afterAcqSharesPer":"0.00","acqfromDt":"20-Dec-2017","acqtoDt":"20-Dec-2017","intimDt":"22-Dec-2017","acqMode":"Market Purchase","derivativeType":"-","exchange":"NA","remarks":"-"},{"symbol":"MOTHERSUMI","company":null,"anex":"7(2)","acqName":"Samvardhana Motherson International Ltd","date":"22-Dec-2017 09:47","pid":"1028629","tkdAcqm":null,"buyValue":"0","sellValue":"0","buyQuantity":"0","sellquantity":"0","secType":"Equity Shares","secAcq":"28991000","did":"148678","tdpTransactionType":"Sell","tdpDerivativeContractType":"-","xbrl":null,"personCategory":"Promoters","befAcqSharesNo":"732824769","befAcqSharesPer":"34.81","secVal":"10872267130","securitiesTypePost":"Equity Shares","afterAcqSharesNo":"703833769","afterAcqSharesPer":"33.43","acqfromDt":"21-Dec-2017","acqtoDt":"21-Dec-2017","intimDt":"21-Dec-2017","acqMode":"Others","derivativeType":"-","exchange":"BSE,NSE","remarks":"-"},{"symbol":"MOTHERSUMI","company":"Motherson Sumi Systems Limited","anex":"7(2)","acqName":"Sumitomo Wiring Systems Limited","date":"26-Sep-2016 11:34","pid":"1010557","tkdAcqm":null,"buyValue":"0","sellValue":"0","buyQuantity":"0","sellquantity":"0","secType":"Equity Shares","secAcq":"17762460","did":"48292","tdpTransactionType":"Buy","tdpDerivativeContractType":"-","xbrl":null,"personCategory":"Promoters","befAcqSharesNo":"334520781","befAcqSharesPer":"25.29","secVal":"5630700000","securitiesTypePost":"Equity Shares","afterAcqSharesNo":"352283241","afterAcqSharesPer":"25.29","acqfromDt":"21-Sep-2016","acqtoDt":"21-Sep-2016","intimDt":"22-Sep-2016","acqMode":"Preferential Offer","derivativeType":"-","exchange":"NA","remarks":"-"}]}